context_collector/__init__.py
context_collector/app.py
context_collector-0.1.0.dist-info/METADATA
context_collector-0.1.0.dist-info/WHEEL
context_collector-0.1.0.dist-info/entry_points.txt
context_collector-0.1.0.dist-info/RECORD
