Metadata-Version: 2.1
Name: context-collector
Version: 0.1.0
Summary: Collect context for llm chat
Author: chen9z
Requires-Python: >=3.10,<4.0
Classifier: Programming Language :: Python :: 3
Classifier: Programming Language :: Python :: 3.10
Classifier: Programming Language :: Python :: 3.11
Classifier: Programming Language :: Python :: 3.12
